{
  "1": {
    "id": 1,
    "ep": "1",
    "season": "1",
    "title_en": "Where Is Everybody?",
    "description_en": "Mike Ferris finds himself alone in the small Oakwood town and without recollection about his name, where he is or who he is. Mike wanders through the town trying to find a living soul. The tension increases and Mike has a breakdown.",
    "title_pt": "Onde Estão Todos?",
    "description_pt": "Mike Ferris se encontra sozinho na pequena cidade de Oakwood e sem se lembrar de seu nome, onde está ou quem é. Mike vagueia pela cidade tentando encontrar uma alma viva. A tensão aumenta e Mike tem um colapso.",
    "img_desktop": "ep-1.jpg",
    "img_mobile": "ep-1-mobile.jpg",
    "released": "2 out 1959",
    "imdb": "8.0",
    "director": "Robert Stevens",
    "writer": "Rod Serling",
    "runtime": "25 min",
    "country": "USA",
    "language": "English",
    "cast": [
      {
        "img": "url",
        "actor": "Earl Holliman",
        "character": "Mike Ferris"
      },
      {
        "img": "url",
        "actor": "James Gregory",
        "character": "Air Force General"
      },
      {
        "img": "url",
        "actor": "Paul Langton",
        "character": "Doctor"
      },
      {
        "img": "url",
        "actor": "James McCallion",
        "character": "Reporter #1"
      },
      {
        "img": "url",
        "actor": "John Conwell",
        "character": "Air Force Colonel"
      },
      {
        "img": "url",
        "actor": "Jay Overholts",
        "character": "Reporter #2"
      },
      {
        "img": "url",
        "actor": "Carter Mullally Jr.",
        "character": "Air Force Captain"
      },
      {
        "img": "url",
        "actor": "Garry Walberg",
        "character": "Reporter #3"
      },
      {
        "img": "url",
        "actor": "Jim Johnson",
        "character": "Air Force Staff Sergeant"
      }
    ]
  },
  "2": {
    "id": 2,
    "ep": "2",
    "season": "1",
    "title_en": "One for the Angels",
    "description_en": "A pitchman is visited by Mr. Death and is forced to get his priorities in order.",
    "title_pt": "Um Negócio Para os Anjos",
    "description_pt": "Um vendedor é visitado pelo Sr. Morte e é forçado a colocar suas prioridades em ordem.",
    "img_desktop": "ep-1.jpg",
    "img_mobile": "ep-1-mobile.jpg",
    "released": "9 October 1959",
    "imdb": "7.7",
    "director": "Robert Parrish",
    "writer": "Rod Serling",
    "runtime": "25 min",
    "country": "USA",
    "language": "English",
    "cast": [
      {
        "img": "url",
        "actor": "Rod Serling",
        "character": "Narrator"
      },
      {
        "img": "url",
        "actor": "Ed Wynn",
        "character": "Lou Bookman"
      },
      {
        "img": "url",
        "actor": "Murray Hamilton",
        "character": "Mr. Death"
      },
      {
        "img": "url",
        "actor": "Dana Dillaway",
        "character": "Maggie Polanski"
      },
      {
        "img": "url",
        "actor": "Jay Overholts",
        "character": "Doctor"
      },
      {
        "img": "url",
        "actor": "Merritt Bohn",
        "character": "Truck Driver"
      }
    ]
  },
  "3": {
    "id": 3,
    "ep": "3",
    "season": "1",
    "title_en": "Mr. Denton on Doomsday",
    "description_en": "The town drunk in the old-west faces his past when Fate lends a hand.",
    "title_pt": "Sr. Denton no Dia do Duelo",
    "description_pt": "Ex-pistoleiro bêbado tem as suas habilidades no gatilho magicamente restauradas.",
    "img_desktop": "ep-1.jpg",
    "img_mobile": "ep-1-mobile.jpg",
    "released": "16 October 1959",
    "imdb": "7.2",
    "director": "Allen Reisner",
    "writer": "Rod Serling",
    "runtime": "25 min",
    "country": "USA",
    "language": "English",
    "cast": [
      {
        "img": "url",
        "actor": "Rod Serling",
        "character": "Narrator"
      },
      {
        "img": "url",
        "actor": "Dan Duryea",
        "character": "Al Denton"
      },
      {
        "img": "url",
        "actor": "Martin Landau",
        "character": "Dan Hotaling"
      },
      {
        "img": "url",
        "actor": "Jeanne Cooper",
        "character": "Liz"
      },
      {
        "img": "url",
        "actor": "Malcolm Atterbury",
        "character": "Henry J. Fate"
      },
      {
        "img": "url",
        "actor": "Ken Lynch",
        "character": "Charlie"
      },
      {
        "img": "url",
        "actor": "Arthur Batanides",
        "character": "Leader"
      },

      {
        "img": "url",
        "actor": "Bill Erwin",
        "character": "Man"
      },
      {
        "img": "url",
        "actor": "Robert Burton",
        "character": "Doctor"
      },
      {
        "img": "url",
        "actor": "Doug McClure",
        "character": "Pete Grant"
      }
      
    ]
  }
}